ament_ruff/__init__.py
ament_ruff/main.py
ament_ruff/pytest_marker.py
ament_ruff/configuration/ruff.toml
ament_ruff-0.0.2.data/data/share/ament_index/resource_index/packages/ament_ruff
ament_ruff-0.0.2.data/data/share/ament_ruff/package.xml
ament_ruff-0.0.2.dist-info/licenses/LICENSE
ament_ruff-0.0.2.dist-info/METADATA
ament_ruff-0.0.2.dist-info/WHEEL
ament_ruff-0.0.2.dist-info/entry_points.txt
ament_ruff-0.0.2.dist-info/top_level.txt
ament_ruff-0.0.2.dist-info/zip-safe
ament_ruff-0.0.2.dist-info/RECORD
