Metadata-Version: 2.4
Name: ament_ruff
Version: 0.0.2
Summary: Python linter/formatter using ruff
Maintainer: Ben Andrew
Maintainer-email: benjamin.andrew@swri.org
License: BSD-3-Clause
License-File: LICENSE
Requires-Dist: argcomplete
Requires-Dist: ruff
Requires-Dist: setuptools
Requires-Dist: unidiff
Dynamic: license
Dynamic: license-file
Dynamic: maintainer
Dynamic: maintainer-email
Dynamic: requires-dist
Dynamic: summary
